{
    "AX": {
        "error": 0.005254119748727726,
        "error_type": "SEM",
        "filter_outliers_dict": {
            "filter_outliers": true,
            "iterations": 1,
            "std_devs": 2
        },
        "fit": "Average",
        "value": 0.01537430056523511
    },
    "CDD": {
        "error": 2.4064945606999145e-05,
        "error_type": "SEM",
        "filter_outliers_dict": {
            "filter_outliers": false,
            "iterations": 1,
            "std_devs": 2
        },
        "fit": "Average",
        "value": 0.00019820418021706702
    },
    "H1": {
        "error": 0.016627106674429997,
        "error_type": "SEM",
        "filter_outliers_dict": {
            "filter_outliers": true,
            "iterations": 1,
            "std_devs": 2
        },
        "fit": "Average",
        "value": -0.012741421171215463
    },
    "L1": {
        "error": 0.006923900171419257,
        "error_type": "SEM",
        "filter_outliers_dict": {
            "filter_outliers": true,
            "iterations": 1,
            "std_devs": 2
        },
        "fit": "Average",
        "value": 0.012940892709854601
    },
    "L2": {
        "error": 0.005989562487245503,
        "error_type": "SEM",
        "filter_outliers_dict": {
            "filter_outliers": false,
            "iterations": 1,
            "std_devs": 2
        },
        "fit": "Average",
        "value": -0.020476039154217526
    }
}